Switches/Switch.v
module mux_4to1(out,s0,s1,i0,i1,i2,i3);

input s0,s1,i0,i1,i2,i3;
output out;

wire t0,t1,t2,t3;

tranif0(i0,t0,s0);
tranif0(t0,out,s1);

tranif1(i1,t1,s0);
tranif0(t1,out,s1);

tranif0(i2,t2,s0);
tranif1(t2,out,s1);

tranif1(i3,t3,s0);
tranif1(t3,out,s1);

endmodule

Switches/switch_test.v

`include "Switch.v"

module mux41_test;

reg s0,s1,i0,i1,i2,i3;
wire out;
integer k;

mux_4to1 DUT (out,s0,s1,i0,i1,i2,i3);

initial begin 
	for (k=0; k<64;k=k+1)
		begin 
			#5 {s0,s1,i0,i1,i2,i3}=k;
			$display ("Sel: %2b, IN: %4b, Out: %b",{s0,s1},{i0,i1,i2,i3},out);
		end
end

initial 
begin 
 $dumpfile ("switch_wave.vcd");
 $dumpvars;
 //$monitor($time,"S0: %b, S1: %b, I0: %b, I1: %b, I2: %b, I3: %b, OUT: %b",s0,s1,i0,i1,i2,i3,out);
 end
endmodule

Switches/switch_wave.vcd
$date
	Thu Mar 22 17:15:47 2018
$end
$version
	Icarus Verilog
$end
$timescale
	1s
$end
$scope module mux41_test $end
$var wire 1 ! out $end
$var reg 1 " i0 $end
$var reg 1 # i1 $end
$var reg 1 $ i2 $end
$var reg 1 % i3 $end
$var reg 1 & s0 $end
$var reg 1 ' s1 $end
$var integer 32 ( k [31:0] $end
$scope module DUT $end
$var wire 1 ) i0 $end
$var wire 1 * i1 $end
$var wire 1 + i2 $end
$var wire 1 , i3 $end
$var wire 1 ! out $end
$var wire 1 & s0 $end
$var wire 1 ' s1 $end
$var wire 1 - t0 $end
$var wire 1 . t1 $end
$var wire 1 / t2 $end
$var wire 1 0 t3 $end
$upscope $end
$upscope $end
$enddefinitions $end
#0
$dumpvars
x0
x/
x.
x-
x,
x+
x*
x)
b0 (
x'
x&
x%
x$
x#
x"
x!
$end
#5
0)
0-
0*
0.
0+
0/
0,
0!
z0
b1 (
0&
0'
0"
0#
0$
0%
#10
1,
b10 (
1%
#15
1+
1/
0,
b11 (
1$
0%
#20
1,
b100 (
1%
#25
1*
0+
0/
0,
b101 (
1#
0$
0%
#30
1,
b110 (
1%
#35
1+
1/
0,
b111 (
1$
0%
#40
1,
b1000 (
1%
#45
1)
1-
0*
1.
0+
0/
0,
1!
b1001 (
1"
0#
0$
0%
#50
1,
b1010 (
1%
#55
1+
1/
0,
b1011 (
1$
0%
#60
1,
b1100 (
1%
#65
1*
0+
0/
0,
b1101 (
1#
0$
0%
#70
1,
b1110 (
1%
#75
1+
1/
0,
b1111 (
1$
0%
#80
1,
b10000 (
1%
#85
0)
0-
0*
z.
0+
0/
0,
0!
00
b10001 (
1'
0"
0#
0$
0%
#90
1,
b10010 (
1%
#95
1+
1/
0,
1!
10
b10011 (
1$
0%
#100
1,
b10100 (
1%
#105
1*
0+
0/
0,
0!
00
b10101 (
1#
0$
0%
#110
1,
b10110 (
1%
#115
1+
1/
0,
1!
10
b10111 (
1$
0%
#120
1,
b11000 (
1%
#125
1)
1-
0*
0+
0/
0,
0!
00
b11001 (
1"
0#
0$
0%
#130
1,
b11010 (
1%
#135
1+
1/
0,
1!
10
b11011 (
1$
0%
#140
1,
b11100 (
1%
#145
1*
0+
0/
0,
0!
00
b11101 (
1#
0$
0%
#150
1,
b11110 (
1%
#155
1+
1/
0,
1!
10
b11111 (
1$
0%
#160
1,
b100000 (
1%
#165
0)
0-
0*
0.
0+
z/
0,
0!
00
b100001 (
1&
0'
0"
0#
0$
0%
#170
1,
10
b100010 (
1%
#175
1+
0,
00
b100011 (
1$
0%
#180
1,
10
b100100 (
1%
#185
1-
1*
1.
0+
0,
1!
00
b100101 (
1#
0$
0%
#190
1,
10
b100110 (
1%
#195
1+
0,
00
b100111 (
1$
0%
#200
1,
10
b101000 (
1%
#205
1)
0-
0*
0.
0+
0,
0!
00
b101001 (
1"
0#
0$
0%
#210
1,
10
b101010 (
1%
#215
1+
0,
00
b101011 (
1$
0%
#220
1,
10
b101100 (
1%
#225
1-
1*
1.
0+
0,
1!
00
b101101 (
1#
0$
0%
#230
1,
10
b101110 (
1%
#235
1+
0,
00
b101111 (
1$
0%
#240
1,
10
b110000 (
1%
#245
0)
z-
0*
0.
0+
0/
0,
0!
00
b110001 (
1'
0"
0#
0$
0%
#250
1/
1,
1!
10
b110010 (
1%
#255
1+
0/
0,
0!
00
b110011 (
1$
0%
#260
1/
1,
1!
10
b110100 (
1%
#265
1*
1.
0+
0/
0,
0!
00
b110101 (
1#
0$
0%
#270
1/
1,
1!
10
b110110 (
1%
#275
1+
0/
0,
0!
00
b110111 (
1$
0%
#280
1/
1,
1!
10
b111000 (
1%
#285
1)
0*
0.
0+
0/
0,
0!
00
b111001 (
1"
0#
0$
0%
#290
1/
1,
1!
10
b111010 (
1%
#295
1+
0/
0,
0!
00
b111011 (
1$
0%
#300
1/
1,
1!
10
b111100 (
1%
#305
1*
1.
0+
0/
0,
0!
00
b111101 (
1#
0$
0%
#310
1/
1,
1!
10
b111110 (
1%
#315
1+
0/
0,
0!
00
b111111 (
1$
0%
#320
1/
1,
1!
10
b1000000 (
1%
