Encoder/Encoder/encodermod.v
module encodermod(d, a, b, c);

input [0:7] d;

output a;

output b;

output c;

or(a,d[4],d[5],d[6],d[7]);

or(b,d[3],d[2],d[6],d[7]);

or(c,d[1],d[3],d[5],d[7]);

endmodule

Encoder/Encoder/encodert_b.v

`include "encodermod.v"

module encodert_b;

reg [0:7] d;

wire a;

wire b;

wire c;

encodermod uut (.d(d), .a(a), .b(b),.c(c) );

initial begin

$dumpfile("encode.vcd");
$dumpvars(0,encodert_b);


#10 d=8'b10000000;

#10 d=8'b01000000;

#10 d=8'b00100000;

#10 d=8'b00010000;

#10 d=8'b00001000;

#10 d=8'b00000100;

#10 d=8'b00000010;

#10 d=8'b00000001;

#10 $finish;

end

initial 
	begin 
		$monitor($time,"\t d=%b, a=%b, b= %b c=%b",d,a,b,c);
	end

endmodule

Encoder/Encoder/encode.vcd
$date
	Thu Feb 08 22:21:33 2018
$end
$version
	Icarus Verilog
$end
$timescale
	1s
$end
$scope module encodert_b $end
$var wire 1 ! c $end
$var wire 1 " b $end
$var wire 1 # a $end
$var reg 8 $ d [0:7] $end
$scope module uut $end
$var wire 1 # a $end
$var wire 1 " b $end
$var wire 1 ! c $end
$var wire 8 % d [0:7] $end
$upscope $end
$upscope $end
$enddefinitions $end
#0
$dumpvars
bx %
bx $
x#
x"
x!
$end
#10
0#
0"
0!
b10000000 $
b10000000 %
#20
1!
b1000000 $
b1000000 %
#30
1"
0!
b100000 $
b100000 %
#40
1!
b10000 $
b10000 %
#50
1#
0"
0!
b1000 $
b1000 %
#60
1!
b100 $
b100 %
#70
1"
0!
b10 $
b10 %
#80
1!
b1 $
b1 %
