FA/fa/Full Adder (gates)/fa_gates.v
module and1(c,a,b);

	output c;
	input a,b;

	assign c=a&b;
endmodule


module xor1(c,a,b);

	output c;
	input a,b;
	assign c=a^b;
endmodule

module fa_gates (s,cout,a,b,cin);
	
	output s,cout;	
	input a,b,cin;
	
	
	xor1 u1 (o1,a,b);
	xor1 u2 (s,o1,cin);
	
	and1 u3 (o2,cin,o1);
	and1 u4 (o3,a,b);
	
	or u5 (cout,o2,o3);

endmodule

FA/fa/Full Adder (gates)/fa_gates_tb.v
`timescale 1ns/100ps

module fa_gates_tb;

reg a,b,cin;

wire out,cout;

integer i;

fa_gates uut (.a(a),.b(b),.cin(cin),.s(out),.cout(cout));

initial 
begin

$dumpfile("fa_g.vcd");
$dumpvars(0,fa_gates_tb);


for (i=0;i<8;i=i+1)

begin
	{a,b,cin}=i; #5;
	
end
#5 $finish;
end

initial 
	begin 
		$monitor($time,"a=%b, b=%b, c=%b, sum=%b, cout=%b",a,b,cin,out,cout);
	end
	
endmodule

FA/fa/Full Adder (gates)/fa_g.vcd
$date
	Sun Dec 10 18:24:56 2017
$end
$version
	Icarus Verilog
$end
$timescale
	100ps
$end
$scope module fa_gates_tb $end
$var wire 1 ! out $end
$var wire 1 " cout $end
$var reg 1 # a $end
$var reg 1 $ b $end
$var reg 1 % cin $end
$var integer 32 & i [31:0] $end
$scope module uut $end
$var wire 1 # a $end
$var wire 1 $ b $end
$var wire 1 % cin $end
$var wire 1 " cout $end
$var wire 1 ! s $end
$var wire 1 ' o3 $end
$var wire 1 ( o2 $end
$var wire 1 ) o1 $end
$scope module u1 $end
$var wire 1 # a $end
$var wire 1 $ b $end
$var wire 1 ) c $end
$upscope $end
$scope module u2 $end
$var wire 1 ) a $end
$var wire 1 % b $end
$var wire 1 ! c $end
$upscope $end
$scope module u3 $end
$var wire 1 % a $end
$var wire 1 ) b $end
$var wire 1 ( c $end
$upscope $end
$scope module u4 $end
$var wire 1 # a $end
$var wire 1 $ b $end
$var wire 1 ' c $end
$upscope $end
$upscope $end
$upscope $end
$enddefinitions $end
#0
$dumpvars
0)
0(
0'
b0 &
0%
0$
0#
0"
0!
$end
#50
1!
1%
b1 &
#100
1)
1!
1$
0%
b10 &
#150
1"
0!
1(
1%
b11 &
#200
0"
1!
0(
1#
0$
0%
b100 &
#250
1"
0!
1(
1%
b101 &
#300
0)
1'
0!
0(
1$
0%
b110 &
#350
1!
1%
b111 &
#400
b1000 &
