FSM/traffic_light.v
module cyclic_lamp(clk,light);

input clk;
output reg [0:2]light;
parameter S0=0,S1=1,S2=2;
parameter RED=3'b100,GREEN=3'b010,YELLOW=3'b001;
reg[0:1]state;
always @(posedge clk)
	case (state)
		S0:begin //Means RED
			light<=GREEN; state<=S1;
			end
		S1: begin  //Means GREEN 
			light <=YELLOW; state<=S2;
			end
		S2:begin 
			light<=RED; state<=S0;
			end
		default:begin 
			light<=RED;
			state<=S0;
			end
	endcase
endmodule

FSM/test_light.v
`include "traffic_light.v"
module test_cyclic_lamp;
	reg clk;
	wire[0:2]light;
	
	cyclic_lamp LAMP (.clk(clk),.light(light));
	
	always #5 clk=~clk;
	
	initial 
	begin 
	clk=1'b0;
	#100 $finish;
	end 
	initial begin 
	$dumpfile ("cyclic.vcd");
	$dumpvars(0,test_cyclic_lamp);
	$monitor ($time, " RGY: %b",light);
	end
endmodule

FSM/cyclic.vcd
$date
	Wed Mar 14 15:33:20 2018
$end
$version
	Icarus Verilog
$end
$timescale
	1s
$end
$scope module test_cyclic_lamp $end
$var wire 3 ! light [0:2] $end
$var reg 1 " clk $end
$scope module LAMP $end
$var wire 1 " clk $end
$var reg 3 # light [0:2] $end
$var reg 2 $ state [0:1] $end
$upscope $end
$upscope $end
$enddefinitions $end
#0
$dumpvars
bx $
bx #
0"
bx !
$end
#5
b0 $
b100 !
b100 #
1"
#10
0"
#15
b1 $
b10 !
b10 #
1"
#20
0"
#25
b10 $
b1 !
b1 #
1"
#30
0"
#35
b0 $
b100 !
b100 #
1"
#40
0"
#45
b1 $
b10 !
b10 #
1"
#50
0"
#55
b10 $
b1 !
b1 #
1"
#60
0"
#65
b0 $
b100 !
b100 #
1"
#70
0"
#75
b1 $
b10 !
b10 #
1"
#80
0"
#85
b10 $
b1 !
b1 #
1"
#90
0"
#95
b0 $
b100 !
b100 #
1"
