JK FF/jk_ff_s.v
// Synchronous JK Flip Flop

module jk_ff_s(input reset,input clk,input j,input k,output reg q,output qb);

assign qb=~q;

always @(posedge clk)
if (~reset)
	q<=1'b0;
else
	case ({j,k})
		2'b00:q<=q;
		2'b01: q<=1'b0;
		2'b10: q<=1'b1;
		2'b11: q<=~q;
	endcase
	
endmodule

JK FF/jk_test.v

`include "jk_ff_s.v"

module test;

reg clk=0;
reg j=0;
reg k=0;
reg reset=1;
wire q, qnot;

jk_ff_s dut(reset, clk,j,k,q,qb);

initial
  begin
    $dumpfile("dump.vcd");
    $dumpvars(1);
	$monitor("clk=%b,Input-> JK =%b%b, Reset = %b, Output-> Q =%b, Qbar=%b",clk,j,k, reset,q,qb);
	
	forever begin
	clk=0;
	#5 clk=1;
	#5 clk=0;
	end
	end
	initial begin
	j=0; k=0; reset=1;
	#4 j=1; k=1; reset=0;
	#40 reset=1;
	#10 j=0; k=1;
	#10 j=1; k=0;
	#10 j=0; k=0;
	#10 j=1; k=1;
	#10 reset=0;
	#10 j=1; k=0;
	#20 $finish;
	end
endmodule

JK FF/dump.vcd
$date
	Mon Mar 19 23:32:43 2018
$end
$version
	Icarus Verilog
$end
$timescale
	1s
$end
$scope module test $end
$var wire 1 ! qb $end
$var wire 1 " q $end
$var reg 1 # clk $end
$var reg 1 $ j $end
$var reg 1 % k $end
$var reg 1 & reset $end
$upscope $end
$enddefinitions $end
#0
$dumpvars
1&
0%
0$
0#
x"
x!
$end
#4
0&
1%
1$
#5
1!
0"
1#
#10
0#
#15
1#
#20
0#
#25
1#
#30
0#
#35
1#
#40
0#
#44
1&
#45
0!
1"
1#
#50
0#
#54
0$
#55
1!
0"
1#
#60
0#
#64
0%
1$
#65
0!
1"
1#
#70
0#
#74
0$
#75
1#
#80
0#
#84
1%
1$
#85
1!
0"
1#
#90
0#
#94
0&
#95
1#
#100
0#
#104
0%
