Shift Register/Shift Register.v
module uni_shift_8b(op,clk,rst_a, load,sh_ro_lt_rt,ip);
  output reg [7:0] op;
  input load;
  input [1:0] sh_ro_lt_rt;
  input [7:0] ip;
  input clk, rst_a;
  
  reg [7:0]temp;
  
  
  
  always @(posedge clk or posedge rst_a)
   begin
     if (rst_a)
       
       op = 0;
      
     else    
       case(load)
         1'b1: 
          begin                            //Load Input
            temp = ip;
          //  op = temp;
          end
         1'b0:                             //Operation 
          case (sh_ro_lt_rt)
            2'b00:  op = temp<<1;     //Left Shift
            2'b01:  op = temp>>1;     //Right Shift
            2'b10:  op = {temp[6:0],temp[7]}; //Rotate Left
            2'b11:  op = {temp[0], temp[7:1]};  //Rotate Right
                   
            default: $display("Invalid Shift Control Input");
          endcase
      
        
         
        default: $display("Invalid Load Control Input");
        endcase
   
    end 
    
  endmodule

Shift Register/Shift_test.v
`timescale 1ns/1ps
`include "Shift Register.v"


module uni_shift_8b_tst;
  reg [7:0] ip;
  reg [1:0] sh_ro_lt_rt;
  reg load,rst_a,clk;
  wire [7:0] op;


   uni_shift_8b u1 (.op(op), .ip(ip), .sh_ro_lt_rt(sh_ro_lt_rt), .load(load) , .rst_a(rst_a) , .clk(clk));

initial
  begin
     clk=1'b1;
     forever #50 clk=~clk;   
  end
  
   initial
     begin
    ip = 8'b11001100;
    rst_a = 1'b1;
    load = 1'b1;
    sh_ro_lt_rt = 2'b00;
    #100;
    
    ip = 8'b10001100;
    rst_a = 1'b0;
    load = 1'b1;
    sh_ro_lt_rt = 2'b01;
    #100;
    
    ip = 8'b11001100;

    load = 1'b0;
    sh_ro_lt_rt = 2'b01;
    #100;
    
    ip = 8'b10101101;
    
    load = 1'b1;
    sh_ro_lt_rt = 2'b01;
    #100;
    
    ip = 8'b11001101;

    load = 1'b0;
    sh_ro_lt_rt = 2'b01;
    #100;

    ip = 8'b11101100;
    load = 1'b1;
    sh_ro_lt_rt = 2'b10;
    #100;

    ip = 8'b11110000;
    load = 1'b0;
    sh_ro_lt_rt = 2'b10;
    #100;

    ip = 8'b11001100;
    load = 1'b1;
    sh_ro_lt_rt = 2'b11;
    #100;

    ip = 8'b11001101;
    load = 1'b0;
    sh_ro_lt_rt = 2'b11;
    #100;
    
    ip = 8'b11001000;
    load = 1'b1;
    sh_ro_lt_rt = 2'b11;
    #100;
    $finish;
 end // initial begin
 
 initial 
 begin 
	$dumpfile("Shift Wave.vcd");
	$dumpvars;
	$monitor("Input=%b, Load = %b, Shift R/L=%b, Output=%b",ip,load,sh_ro_lt_rt,op);
 end
endmodule

Shift Register/Shift Wave.vcd
$date
	Tue Mar 20 11:31:17 2018
$end
$version
	Icarus Verilog
$end
$timescale
	1ps
$end
$scope module uni_shift_8b_tst $end
$var wire 8 ! op [7:0] $end
$var reg 1 " clk $end
$var reg 8 # ip [7:0] $end
$var reg 1 $ load $end
$var reg 1 % rst_a $end
$var reg 2 & sh_ro_lt_rt [1:0] $end
$scope module u1 $end
$var wire 1 " clk $end
$var wire 8 ' ip [7:0] $end
$var wire 1 $ load $end
$var wire 1 % rst_a $end
$var wire 2 ( sh_ro_lt_rt [1:0] $end
$var reg 8 ) op [7:0] $end
$var reg 8 * temp [7:0] $end
$upscope $end
$upscope $end
$enddefinitions $end
#0
$dumpvars
bx *
b0 )
b0 (
b11001100 '
b0 &
1%
1$
b11001100 #
1"
b0 !
$end
#50000
0"
#100000
b10001100 *
1"
b1 &
b1 (
0%
b10001100 #
b10001100 '
#150000
0"
#200000
b1000110 !
b1000110 )
1"
0$
b11001100 #
b11001100 '
#250000
0"
#300000
b10101101 *
1"
1$
b10101101 #
b10101101 '
#350000
0"
#400000
b1010110 !
b1010110 )
1"
0$
b11001101 #
b11001101 '
#450000
0"
#500000
b11101100 *
1"
b10 &
b10 (
1$
b11101100 #
b11101100 '
#550000
0"
#600000
b11011001 !
b11011001 )
1"
0$
b11110000 #
b11110000 '
#650000
0"
#700000
b11001100 *
1"
b11 &
b11 (
1$
b11001100 #
b11001100 '
#750000
0"
#800000
b1100110 !
b1100110 )
1"
0$
b11001101 #
b11001101 '
#850000
0"
#900000
b11001000 *
1"
1$
b11001000 #
b11001000 '
